hotpie.py
hotpie-1.0.5.dist-info/METADATA
hotpie-1.0.5.dist-info/RECORD
hotpie-1.0.5.dist-info/WHEEL
hotpie-1.0.5.dist-info/top_level.txt
