Metadata-Version: 2.1
Name: hotpie
Version: 1.0.5
Summary: OATH HOTP/TOTP implementation in python
Home-page: https://github.com/gingerlime/hotpie
Author: Yoav Aner
Author-email: yoav@gingerlime.com
License: Copyright (C) 2010 Yoav Aner
